{
  "run_id": "fl_fedbn_oral_344486",
  "scalars": {
    "fl/train_loss/client_Spain_Dataset": [
      {
        "step": 1,
        "value": 0.6701902127265931
      },
      {
        "step": 2,
        "value": 0.6019762368996938
      },
      {
        "step": 3,
        "value": 0.5080755287408829
      },
      {
        "step": 4,
        "value": 0.47912519176801044
      },
      {
        "step": 5,
        "value": 0.5325951530536016
      },
      {
        "step": 6,
        "value": 0.3865464722116788
      },
      {
        "step": 7,
        "value": 0.3766736794511477
      },
      {
        "step": 8,
        "value": 0.34355032165845234
      },
      {
        "step": 9,
        "value": 0.31200571164488794
      },
      {
        "step": 10,
        "value": 0.293362675011158
      },
      {
        "step": 11,
        "value": 0.32890298393865425
      },
      {
        "step": 12,
        "value": 0.24583094616731008
      },
      {
        "step": 13,
        "value": 0.20499220830698808
      },
      {
        "step": 14,
        "value": 0.2393123372644186
      },
      {
        "step": 15,
        "value": 0.18224290118863185
      },
      {
        "step": 16,
        "value": 0.18889821014056604
      },
      {
        "step": 17,
        "value": 0.18113472772141298
      },
      {
        "step": 18,
        "value": 0.19323201755682629
      },
      {
        "step": 19,
        "value": 0.14932807938506207
      },
      {
        "step": 20,
        "value": 0.20328188101450603
      },
      {
        "step": 21,
        "value": 0.10460924761525045
      },
      {
        "step": 22,
        "value": 0.1701691389021774
      },
      {
        "step": 23,
        "value": 0.12226179289941987
      },
      {
        "step": 24,
        "value": 0.18733341235667467
      },
      {
        "step": 25,
        "value": 0.12759017572117348
      },
      {
        "step": 26,
        "value": 0.09310405150211105
      },
      {
        "step": 27,
        "value": 0.10763168040973445
      },
      {
        "step": 28,
        "value": 0.12821195796287307
      },
      {
        "step": 29,
        "value": 0.10603959870214263
      },
      {
        "step": 30,
        "value": 0.13092800712989022
      },
      {
        "step": 31,
        "value": 0.13178535570623354
      },
      {
        "step": 32,
        "value": 0.11696380492455015
      },
      {
        "step": 33,
        "value": 0.0782480026455596
      },
      {
        "step": 34,
        "value": 0.10559627257597944
      },
      {
        "step": 35,
        "value": 0.1008398430251206
      },
      {
        "step": 36,
        "value": 0.07624709717114456
      },
      {
        "step": 37,
        "value": 0.0862536651128903
      },
      {
        "step": 38,
        "value": 0.062321895964754126
      },
      {
        "step": 39,
        "value": 0.05947401798485468
      },
      {
        "step": 40,
        "value": 0.15095390058200187
      },
      {
        "step": 41,
        "value": 0.05768326444493141
      },
      {
        "step": 42,
        "value": 0.08445757984707597
      },
      {
        "step": 43,
        "value": 0.08279452455618108
      },
      {
        "step": 44,
        "value": 0.05294401110421556
      },
      {
        "step": 45,
        "value": 0.04590310545274406
      },
      {
        "step": 46,
        "value": 0.053690737101715055
      },
      {
        "step": 47,
        "value": 0.06206833456594419
      },
      {
        "step": 48,
        "value": 0.09393682212976273
      },
      {
        "step": 49,
        "value": 0.05698131225105802
      },
      {
        "step": 50,
        "value": 0.04798127899450871
      }
    ],
    "fl/comp_time_sec/client_Spain_Dataset": [
      {
        "step": 1,
        "value": 152.70809650421143
      },
      {
        "step": 2,
        "value": 156.6724569797516
      },
      {
        "step": 3,
        "value": 154.42646718025208
      },
      {
        "step": 4,
        "value": 157.31136083602905
      },
      {
        "step": 5,
        "value": 156.4816963672638
      },
      {
        "step": 6,
        "value": 158.38793420791626
      },
      {
        "step": 7,
        "value": 159.37514877319336
      },
      {
        "step": 8,
        "value": 155.58304119110107
      },
      {
        "step": 9,
        "value": 158.63675093650818
      },
      {
        "step": 10,
        "value": 157.5913531780243
      },
      {
        "step": 11,
        "value": 153.72310376167297
      },
      {
        "step": 12,
        "value": 154.2174015045166
      },
      {
        "step": 13,
        "value": 153.43875074386597
      },
      {
        "step": 14,
        "value": 156.11022114753723
      },
      {
        "step": 15,
        "value": 156.39178133010864
      },
      {
        "step": 16,
        "value": 162.4118423461914
      },
      {
        "step": 17,
        "value": 160.14469194412231
      },
      {
        "step": 18,
        "value": 156.67663836479187
      },
      {
        "step": 19,
        "value": 159.36312294006348
      },
      {
        "step": 20,
        "value": 154.8139100074768
      },
      {
        "step": 21,
        "value": 152.74437928199768
      },
      {
        "step": 22,
        "value": 161.65669798851013
      },
      {
        "step": 23,
        "value": 158.4660141468048
      },
      {
        "step": 24,
        "value": 159.36971139907837
      },
      {
        "step": 25,
        "value": 153.8336546421051
      },
      {
        "step": 26,
        "value": 155.9767301082611
      },
      {
        "step": 27,
        "value": 157.3255352973938
      },
      {
        "step": 28,
        "value": 157.8125650882721
      },
      {
        "step": 29,
        "value": 161.13107681274414
      },
      {
        "step": 30,
        "value": 156.74413800239563
      },
      {
        "step": 31,
        "value": 156.07476091384888
      },
      {
        "step": 32,
        "value": 158.1285469532013
      },
      {
        "step": 33,
        "value": 151.18764066696167
      },
      {
        "step": 34,
        "value": 153.21862411499023
      },
      {
        "step": 35,
        "value": 154.09470963478088
      },
      {
        "step": 36,
        "value": 155.9817395210266
      },
      {
        "step": 37,
        "value": 156.47313046455383
      },
      {
        "step": 38,
        "value": 154.73857498168945
      },
      {
        "step": 39,
        "value": 160.20049023628235
      },
      {
        "step": 40,
        "value": 173.10820865631104
      },
      {
        "step": 41,
        "value": 154.16349983215332
      },
      {
        "step": 42,
        "value": 153.20638179779053
      },
      {
        "step": 43,
        "value": 155.68080520629883
      },
      {
        "step": 44,
        "value": 156.0338683128357
      },
      {
        "step": 45,
        "value": 158.63386631011963
      },
      {
        "step": 46,
        "value": 158.37585306167603
      },
      {
        "step": 47,
        "value": 158.99263191223145
      },
      {
        "step": 48,
        "value": 156.89179253578186
      },
      {
        "step": 49,
        "value": 158.22945022583008
      },
      {
        "step": 50,
        "value": 159.40331196784973
      }
    ],
    "fl/train_loss/client_Canada_Dataset": [
      {
        "step": 1,
        "value": 0.7454178804429218
      },
      {
        "step": 2,
        "value": 0.5672358180664504
      },
      {
        "step": 3,
        "value": 0.4176329844736744
      },
      {
        "step": 4,
        "value": 0.3294970563531501
      },
      {
        "step": 5,
        "value": 0.2709733380734149
      },
      {
        "step": 6,
        "value": 0.2156607268504726
      },
      {
        "step": 7,
        "value": 0.170952511220435
      },
      {
        "step": 8,
        "value": 0.14075750053459388
      },
      {
        "step": 9,
        "value": 0.13638168753465355
      },
      {
        "step": 10,
        "value": 0.1246900831848951
      },
      {
        "step": 11,
        "value": 0.13147305868811676
      },
      {
        "step": 12,
        "value": 0.10255236729650237
      },
      {
        "step": 13,
        "value": 0.07981099649920191
      },
      {
        "step": 14,
        "value": 0.08428787488907027
      },
      {
        "step": 15,
        "value": 0.07679566692963656
      },
      {
        "step": 16,
        "value": 0.08521751729324294
      },
      {
        "step": 17,
        "value": 0.05182160935503119
      },
      {
        "step": 18,
        "value": 0.08465833433702641
      },
      {
        "step": 19,
        "value": 0.08185912771069939
      },
      {
        "step": 20,
        "value": 0.044433547432113286
      },
      {
        "step": 21,
        "value": 0.057220102777413746
      },
      {
        "step": 22,
        "value": 0.056860937735547665
      },
      {
        "step": 23,
        "value": 0.058334561979949975
      },
      {
        "step": 24,
        "value": 0.06080954647945711
      },
      {
        "step": 25,
        "value": 0.04603966393749466
      },
      {
        "step": 26,
        "value": 0.04605822441872108
      },
      {
        "step": 27,
        "value": 0.08213823345076036
      },
      {
        "step": 28,
        "value": 0.06452195884748045
      },
      {
        "step": 29,
        "value": 0.03022558126413707
      },
      {
        "step": 30,
        "value": 0.05245925692839381
      },
      {
        "step": 31,
        "value": 0.04746517805002988
      },
      {
        "step": 32,
        "value": 0.030520817812958654
      },
      {
        "step": 33,
        "value": 0.0369693942789638
      },
      {
        "step": 34,
        "value": 0.03580203423430292
      },
      {
        "step": 35,
        "value": 0.029012122680690932
      },
      {
        "step": 36,
        "value": 0.02365357966308749
      },
      {
        "step": 37,
        "value": 0.03508690525702722
      },
      {
        "step": 38,
        "value": 0.0683897985767909
      },
      {
        "step": 39,
        "value": 0.027975756518716095
      },
      {
        "step": 40,
        "value": 0.0279243484274944
      },
      {
        "step": 41,
        "value": 0.0667761566130498
      },
      {
        "step": 42,
        "value": 0.020624123289358025
      },
      {
        "step": 43,
        "value": 0.04604506892785645
      },
      {
        "step": 44,
        "value": 0.018056081252498583
      },
      {
        "step": 45,
        "value": 0.033616772918153105
      },
      {
        "step": 46,
        "value": 0.01313894955305944
      },
      {
        "step": 47,
        "value": 0.04016441881751948
      },
      {
        "step": 48,
        "value": 0.05516547157978187
      },
      {
        "step": 49,
        "value": 0.024840192735539432
      },
      {
        "step": 50,
        "value": 0.04631188461485263
      }
    ],
    "fl/comp_time_sec/client_Canada_Dataset": [
      {
        "step": 1,
        "value": 50.1271333694458
      },
      {
        "step": 2,
        "value": 50.35279941558838
      },
      {
        "step": 3,
        "value": 49.88222622871399
      },
      {
        "step": 4,
        "value": 49.580599546432495
      },
      {
        "step": 5,
        "value": 50.21796154975891
      },
      {
        "step": 6,
        "value": 49.484326124191284
      },
      {
        "step": 7,
        "value": 49.13877201080322
      },
      {
        "step": 8,
        "value": 50.22499489784241
      },
      {
        "step": 9,
        "value": 50.601746559143066
      },
      {
        "step": 10,
        "value": 50.30061101913452
      },
      {
        "step": 11,
        "value": 49.597285747528076
      },
      {
        "step": 12,
        "value": 49.308969497680664
      },
      {
        "step": 13,
        "value": 49.82749104499817
      },
      {
        "step": 14,
        "value": 49.37672758102417
      },
      {
        "step": 15,
        "value": 49.88218140602112
      },
      {
        "step": 16,
        "value": 49.89396047592163
      },
      {
        "step": 17,
        "value": 50.10350275039673
      },
      {
        "step": 18,
        "value": 49.78345036506653
      },
      {
        "step": 19,
        "value": 49.824915409088135
      },
      {
        "step": 20,
        "value": 50.004538774490356
      },
      {
        "step": 21,
        "value": 50.147411584854126
      },
      {
        "step": 22,
        "value": 50.62628793716431
      },
      {
        "step": 23,
        "value": 50.27459168434143
      },
      {
        "step": 24,
        "value": 49.444693088531494
      },
      {
        "step": 25,
        "value": 49.323564767837524
      },
      {
        "step": 26,
        "value": 51.60774755477905
      },
      {
        "step": 27,
        "value": 50.894025564193726
      },
      {
        "step": 28,
        "value": 50.43420767784119
      },
      {
        "step": 29,
        "value": 50.09914445877075
      },
      {
        "step": 30,
        "value": 49.657809257507324
      },
      {
        "step": 31,
        "value": 49.71453642845154
      },
      {
        "step": 32,
        "value": 49.27873873710632
      },
      {
        "step": 33,
        "value": 49.60730481147766
      },
      {
        "step": 34,
        "value": 50.58403944969177
      },
      {
        "step": 35,
        "value": 50.370508909225464
      },
      {
        "step": 36,
        "value": 50.01301956176758
      },
      {
        "step": 37,
        "value": 49.7470600605011
      },
      {
        "step": 38,
        "value": 50.51542329788208
      },
      {
        "step": 39,
        "value": 54.745097637176514
      },
      {
        "step": 40,
        "value": 54.86680006980896
      },
      {
        "step": 41,
        "value": 57.7193763256073
      },
      {
        "step": 42,
        "value": 46.675395250320435
      },
      {
        "step": 43,
        "value": 49.48891353607178
      },
      {
        "step": 44,
        "value": 49.87803530693054
      },
      {
        "step": 45,
        "value": 49.76841402053833
      },
      {
        "step": 46,
        "value": 49.967132806777954
      },
      {
        "step": 47,
        "value": 50.05566716194153
      },
      {
        "step": 48,
        "value": 50.63496994972229
      },
      {
        "step": 49,
        "value": 49.91965913772583
      },
      {
        "step": 50,
        "value": 49.654367446899414
      }
    ],
    "fl/train_loss/client_India_Dataset": [
      {
        "step": 1,
        "value": 0.6246490704361349
      },
      {
        "step": 2,
        "value": 0.5719016129150987
      },
      {
        "step": 3,
        "value": 0.575344950115929
      },
      {
        "step": 4,
        "value": 0.44070408345821005
      },
      {
        "step": 5,
        "value": 0.4922075855235259
      },
      {
        "step": 6,
        "value": 0.4267274448648095
      },
      {
        "step": 7,
        "value": 0.3437453494795288
      },
      {
        "step": 8,
        "value": 0.38805149945740897
      },
      {
        "step": 9,
        "value": 0.2975706164725125
      },
      {
        "step": 10,
        "value": 0.3206837061249341
      },
      {
        "step": 11,
        "value": 0.2666550943395123
      },
      {
        "step": 12,
        "value": 0.2430051948176697
      },
      {
        "step": 13,
        "value": 0.27781997438675415
      },
      {
        "step": 14,
        "value": 0.23529750244536748
      },
      {
        "step": 15,
        "value": 0.24904656047874596
      },
      {
        "step": 16,
        "value": 0.22314917933545075
      },
      {
        "step": 17,
        "value": 0.22275443006462106
      },
      {
        "step": 18,
        "value": 0.21627201341713467
      },
      {
        "step": 19,
        "value": 0.17138168502909443
      },
      {
        "step": 20,
        "value": 0.22416559583992543
      },
      {
        "step": 21,
        "value": 0.1671254433943735
      },
      {
        "step": 22,
        "value": 0.2019444276277985
      },
      {
        "step": 23,
        "value": 0.1518994785049775
      },
      {
        "step": 24,
        "value": 0.14304804691346362
      },
      {
        "step": 25,
        "value": 0.1405427016240234
      },
      {
        "step": 26,
        "value": 0.13673914253013209
      },
      {
        "step": 27,
        "value": 0.15088871998644512
      },
      {
        "step": 28,
        "value": 0.17586916771445735
      },
      {
        "step": 29,
        "value": 0.12432676629881219
      },
      {
        "step": 30,
        "value": 0.11540101645853913
      },
      {
        "step": 31,
        "value": 0.12280091367089578
      },
      {
        "step": 32,
        "value": 0.13568881496879234
      },
      {
        "step": 33,
        "value": 0.16442830761176688
      },
      {
        "step": 34,
        "value": 0.09539050564171703
      },
      {
        "step": 35,
        "value": 0.11866089422134489
      },
      {
        "step": 36,
        "value": 0.13294040734278192
      },
      {
        "step": 37,
        "value": 0.12259564420673996
      },
      {
        "step": 38,
        "value": 0.17325294279392742
      },
      {
        "step": 39,
        "value": 0.11457168629749503
      },
      {
        "step": 40,
        "value": 0.10471206105194142
      },
      {
        "step": 41,
        "value": 0.10251854918124081
      },
      {
        "step": 42,
        "value": 0.13993990775149237
      },
      {
        "step": 43,
        "value": 0.08248016172516752
      },
      {
        "step": 44,
        "value": 0.09203301352242003
      },
      {
        "step": 45,
        "value": 0.09391497430897289
      },
      {
        "step": 46,
        "value": 0.06996363011539113
      },
      {
        "step": 47,
        "value": 0.12586426103340878
      },
      {
        "step": 48,
        "value": 0.07369505074196543
      },
      {
        "step": 49,
        "value": 0.06741864399282349
      },
      {
        "step": 50,
        "value": 0.06762100160115854
      }
    ],
    "fl/comp_time_sec/client_India_Dataset": [
      {
        "step": 1,
        "value": 38.145238161087036
      },
      {
        "step": 2,
        "value": 39.98126459121704
      },
      {
        "step": 3,
        "value": 39.86755037307739
      },
      {
        "step": 4,
        "value": 39.642826080322266
      },
      {
        "step": 5,
        "value": 39.71767830848694
      },
      {
        "step": 6,
        "value": 41.662007331848145
      },
      {
        "step": 7,
        "value": 41.14640974998474
      },
      {
        "step": 8,
        "value": 40.76280212402344
      },
      {
        "step": 9,
        "value": 44.035215616226196
      },
      {
        "step": 10,
        "value": 41.48361849784851
      },
      {
        "step": 11,
        "value": 39.06158971786499
      },
      {
        "step": 12,
        "value": 38.96320724487305
      },
      {
        "step": 13,
        "value": 38.7216899394989
      },
      {
        "step": 14,
        "value": 38.92802429199219
      },
      {
        "step": 15,
        "value": 38.87454605102539
      },
      {
        "step": 16,
        "value": 40.10034728050232
      },
      {
        "step": 17,
        "value": 38.935269355773926
      },
      {
        "step": 18,
        "value": 40.565659523010254
      },
      {
        "step": 19,
        "value": 42.03944134712219
      },
      {
        "step": 20,
        "value": 40.45883369445801
      },
      {
        "step": 21,
        "value": 39.38577127456665
      },
      {
        "step": 22,
        "value": 38.843292236328125
      },
      {
        "step": 23,
        "value": 38.310606241226196
      },
      {
        "step": 24,
        "value": 39.669758558273315
      },
      {
        "step": 25,
        "value": 39.8136465549469
      },
      {
        "step": 26,
        "value": 41.00073862075806
      },
      {
        "step": 27,
        "value": 37.47795009613037
      },
      {
        "step": 28,
        "value": 38.17346549034119
      },
      {
        "step": 29,
        "value": 38.94718670845032
      },
      {
        "step": 30,
        "value": 39.71727776527405
      },
      {
        "step": 31,
        "value": 39.58562350273132
      },
      {
        "step": 32,
        "value": 39.090723514556885
      },
      {
        "step": 33,
        "value": 43.175095558166504
      },
      {
        "step": 34,
        "value": 40.43540811538696
      },
      {
        "step": 35,
        "value": 38.723105669021606
      },
      {
        "step": 36,
        "value": 40.570069551467896
      },
      {
        "step": 37,
        "value": 40.37463569641113
      },
      {
        "step": 38,
        "value": 38.876952171325684
      },
      {
        "step": 39,
        "value": 45.85952115058899
      },
      {
        "step": 40,
        "value": 45.57918190956116
      },
      {
        "step": 41,
        "value": 47.31180191040039
      },
      {
        "step": 42,
        "value": 36.486064195632935
      },
      {
        "step": 43,
        "value": 40.19178795814514
      },
      {
        "step": 44,
        "value": 39.01870608329773
      },
      {
        "step": 45,
        "value": 40.20915675163269
      },
      {
        "step": 46,
        "value": 40.523016929626465
      },
      {
        "step": 47,
        "value": 39.801827907562256
      },
      {
        "step": 48,
        "value": 39.521822929382324
      },
      {
        "step": 49,
        "value": 40.33861255645752
      },
      {
        "step": 50,
        "value": 40.30280590057373
      }
    ],
    "fl/comm_cost_bytes/round": [
      {
        "step": 1,
        "value": 134021412.0
      },
      {
        "step": 2,
        "value": 134021412.0
      },
      {
        "step": 3,
        "value": 134021412.0
      },
      {
        "step": 4,
        "value": 134021412.0
      },
      {
        "step": 5,
        "value": 134021412.0
      },
      {
        "step": 6,
        "value": 134021412.0
      },
      {
        "step": 7,
        "value": 134021412.0
      },
      {
        "step": 8,
        "value": 134021412.0
      },
      {
        "step": 9,
        "value": 134021412.0
      },
      {
        "step": 10,
        "value": 134021412.0
      },
      {
        "step": 11,
        "value": 134021412.0
      },
      {
        "step": 12,
        "value": 134021412.0
      },
      {
        "step": 13,
        "value": 134021412.0
      },
      {
        "step": 14,
        "value": 134021412.0
      },
      {
        "step": 15,
        "value": 134021412.0
      },
      {
        "step": 16,
        "value": 134021412.0
      },
      {
        "step": 17,
        "value": 134021412.0
      },
      {
        "step": 18,
        "value": 134021412.0
      },
      {
        "step": 19,
        "value": 134021412.0
      },
      {
        "step": 20,
        "value": 134021412.0
      },
      {
        "step": 21,
        "value": 134021412.0
      },
      {
        "step": 22,
        "value": 134021412.0
      },
      {
        "step": 23,
        "value": 134021412.0
      },
      {
        "step": 24,
        "value": 134021412.0
      },
      {
        "step": 25,
        "value": 134021412.0
      },
      {
        "step": 26,
        "value": 134021412.0
      },
      {
        "step": 27,
        "value": 134021412.0
      },
      {
        "step": 28,
        "value": 134021412.0
      },
      {
        "step": 29,
        "value": 134021412.0
      },
      {
        "step": 30,
        "value": 134021412.0
      },
      {
        "step": 31,
        "value": 134021412.0
      },
      {
        "step": 32,
        "value": 134021412.0
      },
      {
        "step": 33,
        "value": 134021412.0
      },
      {
        "step": 34,
        "value": 134021412.0
      },
      {
        "step": 35,
        "value": 134021412.0
      },
      {
        "step": 36,
        "value": 134021412.0
      },
      {
        "step": 37,
        "value": 134021412.0
      },
      {
        "step": 38,
        "value": 134021412.0
      },
      {
        "step": 39,
        "value": 134021412.0
      },
      {
        "step": 40,
        "value": 134021412.0
      },
      {
        "step": 41,
        "value": 134021412.0
      },
      {
        "step": 42,
        "value": 134021412.0
      },
      {
        "step": 43,
        "value": 134021412.0
      },
      {
        "step": 44,
        "value": 134021412.0
      },
      {
        "step": 45,
        "value": 134021412.0
      },
      {
        "step": 46,
        "value": 134021412.0
      },
      {
        "step": 47,
        "value": 134021412.0
      },
      {
        "step": 48,
        "value": 134021412.0
      },
      {
        "step": 49,
        "value": 134021412.0
      },
      {
        "step": 50,
        "value": 134021412.0
      }
    ],
    "fl/comp_time_sec/round": [
      {
        "step": 1,
        "value": 240.98046803474426
      },
      {
        "step": 2,
        "value": 247.006520986557
      },
      {
        "step": 3,
        "value": 244.17624378204346
      },
      {
        "step": 4,
        "value": 246.5347864627838
      },
      {
        "step": 5,
        "value": 246.41733622550964
      },
      {
        "step": 6,
        "value": 249.5342676639557
      },
      {
        "step": 7,
        "value": 249.66033053398132
      },
      {
        "step": 8,
        "value": 246.57083821296692
      },
      {
        "step": 9,
        "value": 253.27371311187744
      },
      {
        "step": 10,
        "value": 249.37558269500732
      },
      {
        "step": 11,
        "value": 242.38197922706604
      },
      {
        "step": 12,
        "value": 242.4895782470703
      },
      {
        "step": 13,
        "value": 241.98793172836304
      },
      {
        "step": 14,
        "value": 244.4149730205536
      },
      {
        "step": 15,
        "value": 245.14850878715515
      },
      {
        "step": 16,
        "value": 252.40615010261536
      },
      {
        "step": 17,
        "value": 249.18346405029297
      },
      {
        "step": 18,
        "value": 247.02574825286865
      },
      {
        "step": 19,
        "value": 251.2274796962738
      },
      {
        "step": 20,
        "value": 245.27728247642517
      },
      {
        "step": 21,
        "value": 242.27756214141846
      },
      {
        "step": 22,
        "value": 251.12627816200256
      },
      {
        "step": 23,
        "value": 247.05121207237244
      },
      {
        "step": 24,
        "value": 248.48416304588318
      },
      {
        "step": 25,
        "value": 242.97086596488953
      },
      {
        "step": 26,
        "value": 248.58521628379822
      },
      {
        "step": 27,
        "value": 245.6975109577179
      },
      {
        "step": 28,
        "value": 246.42023825645447
      },
      {
        "step": 29,
        "value": 250.1774079799652
      },
      {
        "step": 30,
        "value": 246.119225025177
      },
      {
        "step": 31,
        "value": 245.37492084503174
      },
      {
        "step": 32,
        "value": 246.4980092048645
      },
      {
        "step": 33,
        "value": 243.97004103660583
      },
      {
        "step": 34,
        "value": 244.23807168006897
      },
      {
        "step": 35,
        "value": 243.18832421302795
      },
      {
        "step": 36,
        "value": 246.56482863426208
      },
      {
        "step": 37,
        "value": 246.59482622146606
      },
      {
        "step": 38,
        "value": 244.13095045089722
      },
      {
        "step": 39,
        "value": 260.80510902404785
      },
      {
        "step": 40,
        "value": 273.55419063568115
      },
      {
        "step": 41,
        "value": 259.194678068161
      },
      {
        "step": 42,
        "value": 236.3678412437439
      },
      {
        "step": 43,
        "value": 245.36150670051575
      },
      {
        "step": 44,
        "value": 244.93060970306396
      },
      {
        "step": 45,
        "value": 248.61143708229065
      },
      {
        "step": 46,
        "value": 248.86600279808044
      },
      {
        "step": 47,
        "value": 248.85012698173523
      },
      {
        "step": 48,
        "value": 247.04858541488647
      },
      {
        "step": 49,
        "value": 248.48772192001343
      },
      {
        "step": 50,
        "value": 249.36048531532288
      }
    ],
    "eval/per_hospital/India_Dataset/acc": [
      {
        "step": 1,
        "value": 0.6818181818181818
      },
      {
        "step": 2,
        "value": 0.2878787878787879
      },
      {
        "step": 3,
        "value": 0.5909090909090909
      },
      {
        "step": 4,
        "value": 0.3106060606060606
      },
      {
        "step": 5,
        "value": 0.5151515151515151
      },
      {
        "step": 6,
        "value": 0.4015151515151515
      },
      {
        "step": 7,
        "value": 0.3939393939393939
      },
      {
        "step": 8,
        "value": 0.4166666666666667
      },
      {
        "step": 9,
        "value": 0.42424242424242425
      },
      {
        "step": 10,
        "value": 0.4621212121212121
      },
      {
        "step": 11,
        "value": 0.4166666666666667
      },
      {
        "step": 12,
        "value": 0.4318181818181818
      },
      {
        "step": 13,
        "value": 0.7803030303030303
      },
      {
        "step": 14,
        "value": 0.6666666666666666
      },
      {
        "step": 15,
        "value": 0.6893939393939394
      },
      {
        "step": 16,
        "value": 0.2727272727272727
      },
      {
        "step": 17,
        "value": 0.6060606060606061
      },
      {
        "step": 18,
        "value": 0.6893939393939394
      },
      {
        "step": 19,
        "value": 0.48484848484848486
      },
      {
        "step": 20,
        "value": 0.5681818181818182
      },
      {
        "step": 21,
        "value": 0.7575757575757576
      },
      {
        "step": 22,
        "value": 0.3181818181818182
      },
      {
        "step": 23,
        "value": 0.7803030303030303
      },
      {
        "step": 24,
        "value": 0.7045454545454546
      },
      {
        "step": 25,
        "value": 0.7272727272727273
      },
      {
        "step": 26,
        "value": 0.7651515151515151
      },
      {
        "step": 27,
        "value": 0.7954545454545454
      },
      {
        "step": 28,
        "value": 0.7121212121212122
      },
      {
        "step": 29,
        "value": 0.6136363636363636
      },
      {
        "step": 30,
        "value": 0.7651515151515151
      },
      {
        "step": 31,
        "value": 0.44696969696969696
      },
      {
        "step": 32,
        "value": 0.6060606060606061
      },
      {
        "step": 33,
        "value": 0.29545454545454547
      },
      {
        "step": 34,
        "value": 0.7575757575757576
      },
      {
        "step": 35,
        "value": 0.803030303030303
      },
      {
        "step": 36,
        "value": 0.7878787878787878
      },
      {
        "step": 37,
        "value": 0.7803030303030303
      },
      {
        "step": 38,
        "value": 0.3181818181818182
      },
      {
        "step": 39,
        "value": 0.7651515151515151
      },
      {
        "step": 40,
        "value": 0.803030303030303
      },
      {
        "step": 41,
        "value": 0.6439393939393939
      },
      {
        "step": 42,
        "value": 0.75
      },
      {
        "step": 43,
        "value": 0.7196969696969697
      },
      {
        "step": 44,
        "value": 0.7878787878787878
      },
      {
        "step": 45,
        "value": 0.7803030303030303
      },
      {
        "step": 46,
        "value": 0.8409090909090909
      },
      {
        "step": 47,
        "value": 0.7878787878787878
      },
      {
        "step": 48,
        "value": 0.6666666666666666
      },
      {
        "step": 49,
        "value": 0.7878787878787878
      },
      {
        "step": 50,
        "value": 0.5757575757575758
      }
    ],
    "eval/per_hospital/Canada_Dataset/acc": [
      {
        "step": 1,
        "value": 0.7443609022556391
      },
      {
        "step": 2,
        "value": 0.7869674185463659
      },
      {
        "step": 3,
        "value": 0.8070175438596491
      },
      {
        "step": 4,
        "value": 0.8446115288220551
      },
      {
        "step": 5,
        "value": 0.7243107769423559
      },
      {
        "step": 6,
        "value": 0.8822055137844611
      },
      {
        "step": 7,
        "value": 0.849624060150376
      },
      {
        "step": 8,
        "value": 0.8621553884711779
      },
      {
        "step": 9,
        "value": 0.8947368421052632
      },
      {
        "step": 10,
        "value": 0.8646616541353384
      },
      {
        "step": 11,
        "value": 0.8621553884711779
      },
      {
        "step": 12,
        "value": 0.8571428571428571
      },
      {
        "step": 13,
        "value": 0.8421052631578947
      },
      {
        "step": 14,
        "value": 0.8621553884711779
      },
      {
        "step": 15,
        "value": 0.8872180451127819
      },
      {
        "step": 16,
        "value": 0.8421052631578947
      },
      {
        "step": 17,
        "value": 0.8822055137844611
      },
      {
        "step": 18,
        "value": 0.8847117794486216
      },
      {
        "step": 19,
        "value": 0.8897243107769424
      },
      {
        "step": 20,
        "value": 0.8872180451127819
      },
      {
        "step": 21,
        "value": 0.8872180451127819
      },
      {
        "step": 22,
        "value": 0.8796992481203008
      },
      {
        "step": 23,
        "value": 0.8872180451127819
      },
      {
        "step": 24,
        "value": 0.8847117794486216
      },
      {
        "step": 25,
        "value": 0.8847117794486216
      },
      {
        "step": 26,
        "value": 0.8947368421052632
      },
      {
        "step": 27,
        "value": 0.899749373433584
      },
      {
        "step": 28,
        "value": 0.8897243107769424
      },
      {
        "step": 29,
        "value": 0.8922305764411027
      },
      {
        "step": 30,
        "value": 0.8872180451127819
      },
      {
        "step": 31,
        "value": 0.8897243107769424
      },
      {
        "step": 32,
        "value": 0.8922305764411027
      },
      {
        "step": 33,
        "value": 0.8872180451127819
      },
      {
        "step": 34,
        "value": 0.8796992481203008
      },
      {
        "step": 35,
        "value": 0.8822055137844611
      },
      {
        "step": 36,
        "value": 0.8947368421052632
      },
      {
        "step": 37,
        "value": 0.8621553884711779
      },
      {
        "step": 38,
        "value": 0.8897243107769424
      },
      {
        "step": 39,
        "value": 0.8972431077694235
      },
      {
        "step": 40,
        "value": 0.9022556390977443
      },
      {
        "step": 41,
        "value": 0.8897243107769424
      },
      {
        "step": 42,
        "value": 0.8796992481203008
      },
      {
        "step": 43,
        "value": 0.8796992481203008
      },
      {
        "step": 44,
        "value": 0.9172932330827067
      },
      {
        "step": 45,
        "value": 0.8822055137844611
      },
      {
        "step": 46,
        "value": 0.9022556390977443
      },
      {
        "step": 47,
        "value": 0.8796992481203008
      },
      {
        "step": 48,
        "value": 0.8696741854636592
      },
      {
        "step": 49,
        "value": 0.8922305764411027
      },
      {
        "step": 50,
        "value": 0.8646616541353384
      }
    ],
    "eval/per_hospital/Spain_Dataset/acc": [
      {
        "step": 1,
        "value": 0.37735849056603776
      },
      {
        "step": 2,
        "value": 0.42452830188679247
      },
      {
        "step": 3,
        "value": 0.4339622641509434
      },
      {
        "step": 4,
        "value": 0.6037735849056604
      },
      {
        "step": 5,
        "value": 0.5094339622641509
      },
      {
        "step": 6,
        "value": 0.6509433962264151
      },
      {
        "step": 7,
        "value": 0.46226415094339623
      },
      {
        "step": 8,
        "value": 0.6320754716981132
      },
      {
        "step": 9,
        "value": 0.6509433962264151
      },
      {
        "step": 10,
        "value": 0.5943396226415094
      },
      {
        "step": 11,
        "value": 0.6509433962264151
      },
      {
        "step": 12,
        "value": 0.6037735849056604
      },
      {
        "step": 13,
        "value": 0.6320754716981132
      },
      {
        "step": 14,
        "value": 0.5283018867924528
      },
      {
        "step": 15,
        "value": 0.7075471698113207
      },
      {
        "step": 16,
        "value": 0.6792452830188679
      },
      {
        "step": 17,
        "value": 0.8018867924528302
      },
      {
        "step": 18,
        "value": 0.7547169811320755
      },
      {
        "step": 19,
        "value": 0.6792452830188679
      },
      {
        "step": 20,
        "value": 0.7169811320754716
      },
      {
        "step": 21,
        "value": 0.6886792452830188
      },
      {
        "step": 22,
        "value": 0.7358490566037735
      },
      {
        "step": 23,
        "value": 0.7924528301886793
      },
      {
        "step": 24,
        "value": 0.6415094339622641
      },
      {
        "step": 25,
        "value": 0.7735849056603774
      },
      {
        "step": 26,
        "value": 0.8679245283018868
      },
      {
        "step": 27,
        "value": 0.8490566037735849
      },
      {
        "step": 28,
        "value": 0.8113207547169812
      },
      {
        "step": 29,
        "value": 0.7547169811320755
      },
      {
        "step": 30,
        "value": 0.8490566037735849
      },
      {
        "step": 31,
        "value": 0.8113207547169812
      },
      {
        "step": 32,
        "value": 0.6886792452830188
      },
      {
        "step": 33,
        "value": 0.839622641509434
      },
      {
        "step": 34,
        "value": 0.8018867924528302
      },
      {
        "step": 35,
        "value": 0.7547169811320755
      },
      {
        "step": 36,
        "value": 0.7075471698113207
      },
      {
        "step": 37,
        "value": 0.7169811320754716
      },
      {
        "step": 38,
        "value": 0.7264150943396226
      },
      {
        "step": 39,
        "value": 0.8207547169811321
      },
      {
        "step": 40,
        "value": 0.5283018867924528
      },
      {
        "step": 41,
        "value": 0.7641509433962265
      },
      {
        "step": 42,
        "value": 0.7075471698113207
      },
      {
        "step": 43,
        "value": 0.839622641509434
      },
      {
        "step": 44,
        "value": 0.8018867924528302
      },
      {
        "step": 45,
        "value": 0.6792452830188679
      },
      {
        "step": 46,
        "value": 0.8490566037735849
      },
      {
        "step": 47,
        "value": 0.7924528301886793
      },
      {
        "step": 48,
        "value": 0.7169811320754716
      },
      {
        "step": 49,
        "value": 0.839622641509434
      },
      {
        "step": 50,
        "value": 0.8679245283018868
      }
    ],
    "eval/fedbn_per_hospital/Spain_Dataset/acc": [
      {
        "step": 50,
        "value": 0.8679245283018868
      }
    ],
    "eval/fedbn_per_hospital/Spain_Dataset/loss": [
      {
        "step": 50,
        "value": 0.7620329103377863
      }
    ],
    "eval/fedbn_per_hospital/Canada_Dataset/acc": [
      {
        "step": 50,
        "value": 0.8646616541353384
      }
    ],
    "eval/fedbn_per_hospital/Canada_Dataset/loss": [
      {
        "step": 50,
        "value": 0.47821578278876187
      }
    ],
    "eval/fedbn_per_hospital/India_Dataset/acc": [
      {
        "step": 50,
        "value": 0.5757575757575758
      }
    ],
    "eval/fedbn_per_hospital/India_Dataset/loss": [
      {
        "step": 50,
        "value": 3.604815067651736
      }
    ],
    "eval/fedbn_weighted_overall/acc": [
      {
        "step": 50,
        "value": 0.8053375196232339
      }
    ],
    "eval/fedbn_weighted_overall/loss": [
      {
        "step": 50,
        "value": 1.1733425035456053
      }
    ],
    "eval/overall/acc": [
      {
        "step": 50,
        "value": 0.8053375196232339
      }
    ],
    "eval/overall/loss": [
      {
        "step": 50,
        "value": 1.1733425035456053
      }
    ],
    "eval/classification/accuracy": [
      {
        "step": 50,
        "value": 0.8053375196232339
      }
    ],
    "eval/classification/macro_precision": [
      {
        "step": 50,
        "value": 0.7619315358829707
      }
    ],
    "eval/classification/macro_recall": [
      {
        "step": 50,
        "value": 0.7864259089482207
      }
    ],
    "eval/classification/macro_f1": [
      {
        "step": 50,
        "value": 0.7632808774439676
      }
    ],
    "eval/classification/weighted_precision": [
      {
        "step": 50,
        "value": 0.8194049654642043
      }
    ],
    "eval/classification/weighted_recall": [
      {
        "step": 50,
        "value": 0.8053375196232339
      }
    ],
    "eval/classification/weighted_f1": [
      {
        "step": 50,
        "value": 0.805740251804283
      }
    ],
    "eval/per_class/Benign/precision": [
      {
        "step": 50,
        "value": 0.886039886039886
      }
    ],
    "eval/per_class/Benign/recall": [
      {
        "step": 50,
        "value": 0.8936781609195402
      }
    ],
    "eval/per_class/Benign/f1": [
      {
        "step": 50,
        "value": 0.8898426323319027
      }
    ],
    "eval/per_class/Benign/acc": [
      {
        "step": 50,
        "value": 0.8936781609195402
      }
    ],
    "eval/per_class/Potentially_Malignant/precision": [
      {
        "step": 50,
        "value": 0.8145695364238411
      }
    ],
    "eval/per_class/Potentially_Malignant/recall": [
      {
        "step": 50,
        "value": 0.634020618556701
      }
    ],
    "eval/per_class/Potentially_Malignant/f1": [
      {
        "step": 50,
        "value": 0.7130434782608696
      }
    ],
    "eval/per_class/Potentially_Malignant/acc": [
      {
        "step": 50,
        "value": 0.634020618556701
      }
    ],
    "eval/per_class/Malignant/precision": [
      {
        "step": 50,
        "value": 0.5851851851851851
      }
    ],
    "eval/per_class/Malignant/recall": [
      {
        "step": 50,
        "value": 0.8315789473684211
      }
    ],
    "eval/per_class/Malignant/f1": [
      {
        "step": 50,
        "value": 0.6869565217391305
      }
    ],
    "eval/per_class/Malignant/acc": [
      {
        "step": 50,
        "value": 0.8315789473684211
      }
    ]
  },
  "final": {
    "eval/overall/acc": 0.8053375196232339,
    "eval/overall/loss": 1.1733425035456053,
    "eval/classification/accuracy": 0.8053375196232339,
    "eval/classification/macro_precision": 0.7619315358829707,
    "eval/classification/macro_recall": 0.7864259089482207,
    "eval/classification/macro_f1": 0.7632808774439676,
    "eval/classification/weighted_precision": 0.8194049654642043,
    "eval/classification/weighted_recall": 0.8053375196232339,
    "eval/classification/weighted_f1": 0.805740251804283,
    "eval/per_hospital/Spain_Dataset/acc": 0.8679245283018868,
    "eval/per_hospital/Spain_Dataset/loss": 0.7620329103377863,
    "eval/fedbn_per_hospital/Spain_Dataset/acc": 0.8679245283018868,
    "eval/fedbn_per_hospital/Spain_Dataset/loss": 0.7620329103377863,
    "eval/per_hospital/Canada_Dataset/acc": 0.8646616541353384,
    "eval/per_hospital/Canada_Dataset/loss": 0.47821578278876187,
    "eval/fedbn_per_hospital/Canada_Dataset/acc": 0.8646616541353384,
    "eval/fedbn_per_hospital/Canada_Dataset/loss": 0.47821578278876187,
    "eval/per_hospital/India_Dataset/acc": 0.5757575757575758,
    "eval/per_hospital/India_Dataset/loss": 3.604815067651736,
    "eval/fedbn_per_hospital/India_Dataset/acc": 0.5757575757575758,
    "eval/fedbn_per_hospital/India_Dataset/loss": 3.604815067651736,
    "eval/fedbn_weighted_overall/acc": 0.8053375196232339,
    "eval/fedbn_weighted_overall/loss": 1.1733425035456053,
    "eval/per_class/Benign/acc": 0.8936781609195402,
    "eval/per_class/Benign/precision": 0.886039886039886,
    "eval/per_class/Benign/recall": 0.8936781609195402,
    "eval/per_class/Benign/f1": 0.8898426323319027,
    "eval/per_class/Potentially_Malignant/acc": 0.634020618556701,
    "eval/per_class/Potentially_Malignant/precision": 0.8145695364238411,
    "eval/per_class/Potentially_Malignant/recall": 0.634020618556701,
    "eval/per_class/Potentially_Malignant/f1": 0.7130434782608696,
    "eval/per_class/Malignant/acc": 0.8315789473684211,
    "eval/per_class/Malignant/precision": 0.5851851851851851,
    "eval/per_class/Malignant/recall": 0.8315789473684211,
    "eval/per_class/Malignant/f1": 0.6869565217391305
  },
  "classification": {
    "eval/classification": {
      "tag": "eval/classification",
      "num_samples": 637,
      "accuracy": 0.8053375196232339,
      "macro_precision": 0.7619315358829707,
      "macro_recall": 0.7864259089482207,
      "macro_f1": 0.7632808774439676,
      "weighted_precision": 0.8194049654642043,
      "weighted_recall": 0.8053375196232339,
      "weighted_f1": 0.805740251804283,
      "labels": [
        0,
        1,
        2
      ],
      "class_names": [
        "Benign",
        "Potentially_Malignant",
        "Malignant"
      ],
      "per_class": {
        "Benign": {
          "class_id": 0,
          "precision": 0.886039886039886,
          "recall": 0.8936781609195402,
          "f1": 0.8898426323319027,
          "support": 348,
          "tp": 311,
          "fp": 40,
          "fn": 37
        },
        "Potentially_Malignant": {
          "class_id": 1,
          "precision": 0.8145695364238411,
          "recall": 0.634020618556701,
          "f1": 0.7130434782608696,
          "support": 194,
          "tp": 123,
          "fp": 28,
          "fn": 71
        },
        "Malignant": {
          "class_id": 2,
          "precision": 0.5851851851851851,
          "recall": 0.8315789473684211,
          "f1": 0.6869565217391305,
          "support": 95,
          "tp": 79,
          "fp": 56,
          "fn": 16
        }
      },
      "confusion_matrix": [
        [
          311,
          26,
          11
        ],
        [
          26,
          123,
          45
        ],
        [
          14,
          2,
          79
        ]
      ]
    }
  }
}